{
    "JHU_CSSE-CSSE_Ensemble": {
        "target_end_date": [
            "2024-12-07",
            "2024-12-14",
            "2024-12-21",
            "2024-12-28"
        ],
        "q0.025": [
            0.0,
            0.0,
            0.0,
            0.0
        ],
        "q0.25": [
            0.0,
            1.0,
            0.0,
            4.5
        ],
        "q0.5": [
            1.5,
            4.0,
            6.0,
            13.5
        ],
        "q0.75": [
            4.5,
            11.0,
            14.0,
            23.5
        ],
        "q0.975": [
            12.5,
            23.024999999999977,
            30.0,
            50.5
        ]
    },
    "MIGHTE-Joint": {
        "target_end_date": [
            "2024-12-07",
            "2024-12-14",
            "2024-12-21",
            "2024-12-28"
        ],
        "q0.025": [
            1.0,
            1.0,
            0.0,
            0.0
        ],
        "q0.25": [
            4.0,
            5.0,
            4.0,
            4.0
        ],
        "q0.5": [
            5.0,
            7.0,
            9.0,
            11.0
        ],
        "q0.75": [
            7.0,
            10.0,
            16.0,
            19.0
        ],
        "q0.975": [
            12.0,
            18.0,
            32.0,
            38.0
        ]
    },
    "LUcompUncertLab-chimera": {
        "target_end_date": [
            "2024-11-30",
            "2024-12-07",
            "2024-12-14",
            "2024-12-21",
            "2024-12-28"
        ],
        "q0.025": [
            1,
            1,
            2,
            3,
            2
        ],
        "q0.25": [
            3,
            3,
            6,
            6,
            6
        ],
        "q0.5": [
            4,
            5,
            8,
            9,
            8
        ],
        "q0.75": [
            6,
            8,
            12,
            14,
            12
        ],
        "q0.975": [
            13,
            16,
            24,
            30,
            22
        ]
    },
    "UGA_flucast-Copycat": {
        "target_end_date": [
            "2024-12-07",
            "2024-12-14",
            "2024-12-21",
            "2024-12-28"
        ],
        "q0.025": [
            0.0,
            0.0,
            0.0,
            0.0
        ],
        "q0.25": [
            1.0,
            2.0,
            3.0,
            3.0
        ],
        "q0.5": [
            3.0,
            4.0,
            5.0,
            6.0
        ],
        "q0.75": [
            4.0,
            6.0,
            8.0,
            9.0
        ],
        "q0.975": [
            8.0,
            11.0,
            16.0,
            21.0
        ]
    },
    "UI_CompEpi-EpiGen": {
        "target_end_date": [
            "2024-11-30",
            "2024-12-07",
            "2024-12-14",
            "2024-12-21",
            "2024-12-28"
        ],
        "q0.025": [
            0,
            0,
            0,
            0,
            0
        ],
        "q0.25": [
            0,
            1,
            2,
            3,
            5
        ],
        "q0.5": [
            0,
            1,
            3,
            4,
            6
        ],
        "q0.75": [
            1,
            3,
            4,
            6,
            8
        ],
        "q0.975": [
            36,
            38,
            31,
            22,
            42
        ]
    },
    "UGA_flucast-Scenariocast": {
        "target_end_date": [
            "2024-12-07",
            "2024-12-14",
            "2024-12-21",
            "2024-12-28"
        ],
        "q0.025": [
            0.0,
            0.0,
            1.0,
            3.0
        ],
        "q0.25": [
            1.0,
            3.0,
            6.0,
            11.0
        ],
        "q0.5": [
            3.0,
            6.0,
            10.0,
            16.0
        ],
        "q0.75": [
            6.0,
            9.0,
            15.0,
            24.0
        ],
        "q0.975": [
            11.0,
            17.0,
            27.0,
            46.0
        ]
    },
    "UMass-flusion": {
        "target_end_date": [
            "2024-12-07",
            "2024-12-14",
            "2024-12-21",
            "2024-12-28"
        ],
        "q0.025": [
            0.0,
            0.0,
            0.0,
            0.0
        ],
        "q0.25": [
            1.04850963867086,
            1.35301282582467,
            1.66463038814738,
            2.00338247130304
        ],
        "q0.5": [
            2.73174179174287,
            3.8700912478151,
            5.40327143599368,
            6.83478359712441
        ],
        "q0.75": [
            4.9479660711233,
            7.39528367941479,
            10.7114114648235,
            14.3782104648587
        ],
        "q0.975": [
            12.068417298837,
            19.8960725472539,
            29.7121159691694,
            43.9423334965695
        ]
    },
    "UMass-trends_ensemble": {
        "target_end_date": [
            "2024-12-07",
            "2024-12-14",
            "2024-12-21",
            "2024-12-28"
        ],
        "q0.025": [
            0.5,
            0.0,
            0.0,
            0.0
        ],
        "q0.25": [
            1.0,
            1.0,
            1.0,
            1.0
        ],
        "q0.5": [
            2.0,
            2.0,
            2.5,
            2.5
        ],
        "q0.75": [
            3.0,
            4.0,
            4.0,
            4.0
        ],
        "q0.975": [
            4.5,
            6.0,
            7.0,
            8.5
        ]
    },
    "PSI-PROF": {
        "target_end_date": [
            "2024-12-07",
            "2024-12-14",
            "2024-12-21",
            "2024-12-28"
        ],
        "q0.025": [
            0.0,
            0.0,
            0.0,
            0.0
        ],
        "q0.25": [
            1.0,
            1.0,
            1.0,
            1.0
        ],
        "q0.5": [
            2.0,
            2.49,
            3.0,
            3.0
        ],
        "q0.75": [
            4.0,
            5.0,
            6.0,
            7.0
        ],
        "q0.975": [
            19.61,
            33.45,
            55.05,
            66.33
        ]
    },
    "NEU_ISI-AdaptiveEnsemble": {
        "target_end_date": [
            "2024-12-07",
            "2024-12-14",
            "2024-12-21",
            "2024-12-28"
        ],
        "q0.025": [
            1.0,
            2.0,
            2.0,
            2.0
        ],
        "q0.25": [
            3.0,
            5.0,
            10.0,
            9.0
        ],
        "q0.5": [
            5.0,
            8.0,
            13.0,
            20.0
        ],
        "q0.75": [
            7.0,
            13.0,
            17.0,
            27.0
        ],
        "q0.975": [
            16.0,
            22.0,
            35.0,
            65.0
        ]
    },
    "VTSanghani-PRIME": {
        "target_end_date": [
            "2024-11-30",
            "2024-12-07",
            "2024-12-14",
            "2024-12-21",
            "2024-12-28"
        ],
        "q0.025": [
            0.0,
            0.0,
            0.0,
            1.0,
            16.0
        ],
        "q0.25": [
            7.0,
            6.0,
            9.0,
            14.0,
            32.0
        ],
        "q0.5": [
            14.0,
            12.0,
            18.0,
            29.0,
            49.0
        ],
        "q0.75": [
            21.0,
            18.0,
            27.0,
            43.0,
            67.0
        ],
        "q0.975": [
            28.0,
            24.0,
            35.0,
            57.0,
            82.0
        ]
    },
    "UGA_flucast-INFLAenza": {
        "target_end_date": [
            "2024-12-07",
            "2024-12-14",
            "2024-12-21",
            "2024-12-28"
        ],
        "q0.025": [
            0,
            0,
            0,
            0
        ],
        "q0.25": [
            1,
            2,
            3,
            3
        ],
        "q0.5": [
            3,
            4,
            5,
            6
        ],
        "q0.75": [
            5,
            6,
            9,
            11
        ],
        "q0.975": [
            11,
            15,
            23,
            30
        ]
    },
    "MOBS-GLEAM_FLUH": {
        "target_end_date": [
            "2024-11-30",
            "2024-12-07",
            "2024-12-14",
            "2024-12-21",
            "2024-12-28"
        ],
        "q0.025": [
            1.45,
            3.069,
            3.251,
            2.681,
            1.928
        ],
        "q0.25": [
            1.745,
            5.526,
            6.511,
            6.054,
            5.392
        ],
        "q0.5": [
            2.032,
            6.674,
            9.312,
            10.691,
            10.306
        ],
        "q0.75": [
            2.317,
            8.225,
            12.504,
            16.251,
            19.119
        ],
        "q0.975": [
            2.577,
            12.579,
            19.704,
            26.853,
            34.593
        ]
    },
    "ISU_NiemiLab-GPE": {
        "target_end_date": [
            "2024-11-30",
            "2024-12-07",
            "2024-12-14",
            "2024-12-21",
            "2024-12-28"
        ],
        "q0.025": [
            0.0246474406667086,
            1.51042328755985,
            0.0339536521339976,
            0.0631787512354722,
            0.129557018548441
        ],
        "q0.25": [
            0.211586087874539,
            3.47067563373617,
            3.46523958300777,
            3.57701206994326,
            3.88971493445714
        ],
        "q0.5": [
            0.446010150163326,
            5.91495024813899,
            7.67734488998982,
            9.63541934542828,
            13.2444771126157
        ],
        "q0.75": [
            0.86485196426062,
            8.62275657268121,
            13.8877764758829,
            22.6576718787507,
            37.2860388003364
        ],
        "q0.975": [
            1.75337544469266,
            15.673053905502,
            35.7483442755811,
            88.0515148647014,
            234.156372771087
        ]
    },
    "PSI-PROF_beta": {
        "target_end_date": [
            "2024-12-07",
            "2024-12-14",
            "2024-12-21",
            "2024-12-28"
        ],
        "q0.025": [
            0.0,
            0.0,
            0.0,
            0.0
        ],
        "q0.25": [
            2.0,
            2.0,
            2.0,
            2.3
        ],
        "q0.5": [
            5.0,
            7.0,
            10.71,
            14.0
        ],
        "q0.75": [
            11.0,
            15.0,
            20.0,
            26.0
        ],
        "q0.975": [
            25.0,
            31.0,
            38.0,
            51.0
        ]
    },
    "MIGHTE-Nsemble": {
        "target_end_date": [
            "2024-12-07",
            "2024-12-14",
            "2024-12-21",
            "2024-12-28"
        ],
        "q0.025": [
            0.0,
            0.0,
            0.0,
            0.0
        ],
        "q0.25": [
            2.0,
            3.0,
            5.0,
            5.0
        ],
        "q0.5": [
            4.0,
            6.0,
            10.0,
            12.0
        ],
        "q0.75": [
            7.0,
            10.0,
            16.0,
            20.0
        ],
        "q0.975": [
            13.0,
            19.0,
            32.0,
            38.0
        ]
    },
    "UGuelph-CompositeCurve": {
        "target_end_date": [
            "2024-11-30",
            "2024-12-07",
            "2024-12-14",
            "2024-12-21",
            "2024-12-28"
        ],
        "q0.025": [
            4,
            7,
            12,
            20,
            30
        ],
        "q0.25": [
            4,
            7,
            12,
            20,
            30
        ],
        "q0.5": [
            4,
            7,
            12,
            20,
            30
        ],
        "q0.75": [
            4,
            7,
            12,
            20,
            30
        ],
        "q0.975": [
            4,
            7,
            12,
            20,
            30
        ]
    },
    "FluSight-lop_norm": {
        "target_end_date": [
            "2024-11-30",
            "2024-12-07",
            "2024-12-14",
            "2024-12-21",
            "2024-12-28"
        ],
        "q0.025": [
            0,
            0,
            0,
            0,
            0
        ],
        "q0.25": [
            0,
            1,
            1,
            1,
            2
        ],
        "q0.5": [
            3,
            3,
            5,
            6,
            7
        ],
        "q0.75": [
            6,
            7,
            10,
            14,
            19
        ],
        "q0.975": [
            27,
            23,
            34,
            53,
            79
        ]
    },
    "CU-ensemble": {
        "target_end_date": [
            "2024-12-07",
            "2024-12-14",
            "2024-12-21",
            "2024-12-28"
        ],
        "q0.025": [
            0.0,
            0.0,
            0.0,
            0.0
        ],
        "q0.25": [
            0.0,
            4.0,
            4.0,
            5.0
        ],
        "q0.5": [
            3.0,
            7.0,
            10.0,
            13.0
        ],
        "q0.75": [
            9.0,
            12.0,
            18.0,
            26.0
        ],
        "q0.975": [
            27.0,
            35.0,
            48.0,
            58.0
        ]
    },
    "CMU-TimeSeries": {
        "target_end_date": [
            "2024-11-30",
            "2024-12-07",
            "2024-12-14",
            "2024-12-21",
            "2024-12-28"
        ],
        "q0.025": [
            0.1609767796416522,
            0.3023062790182229,
            0.3291578146114979,
            0.340108844983252,
            0.3394850229663754
        ],
        "q0.25": [
            0.2141155727028418,
            1.14885320250234,
            3.0551930394777806,
            2.759233391526544,
            2.955351975273888
        ],
        "q0.5": [
            1.274786636194212,
            2.3505040823989307,
            5.060343902102948,
            7.569560519503321,
            13.052450244951174
        ],
        "q0.75": [
            4.69728350109796,
            28.75909300360041,
            53.32249738983176,
            82.64967039134739,
            128.14189690232254
        ],
        "q0.975": [
            102.04513988983324,
            178.63453380874313,
            195.22744625124105,
            204.66993650425263,
            204.83038638446337
        ]
    },
    "FluSight-ensemble": {
        "target_end_date": [
            "2024-11-30",
            "2024-12-07",
            "2024-12-14",
            "2024-12-21",
            "2024-12-28"
        ],
        "q0.025": [
            0.0,
            0.0,
            0.0,
            0.0,
            0.0
        ],
        "q0.25": [
            0.0,
            1.0,
            2.0,
            2.0,
            3.0
        ],
        "q0.5": [
            3.0,
            3.0,
            4.0,
            6.0,
            7.0
        ],
        "q0.75": [
            5.0,
            7.0,
            10.0,
            14.0,
            18.0
        ],
        "q0.975": [
            15.0,
            13.0,
            20.0,
            30.0,
            38.0
        ]
    },
    "UMass-AR2": {
        "target_end_date": [
            "2024-12-07",
            "2024-12-14",
            "2024-12-21",
            "2024-12-28"
        ],
        "q0.025": [
            0.0,
            0.0,
            0.0,
            0.0
        ],
        "q0.25": [
            0.5716496426797626,
            0.2367214589235162,
            0.0074144714572349,
            0.1277158202056695
        ],
        "q0.5": [
            2.5389714351339814,
            3.119217650432621,
            3.656620439180088,
            4.2159475503272095
        ],
        "q0.75": [
            5.223077847701395,
            7.330979717797169,
            9.31831309355271,
            11.33154979237109
        ],
        "q0.975": [
            12.481527282986272,
            20.926571529000288,
            28.324674153905573,
            36.54110204473722
        ]
    },
    "FluSight-baseline": {
        "target_end_date": [
            "2024-11-30",
            "2024-12-07",
            "2024-12-14",
            "2024-12-21",
            "2024-12-28"
        ],
        "q0.025": [
            2,
            0,
            0,
            0,
            0
        ],
        "q0.25": [
            2,
            0,
            0,
            0,
            0
        ],
        "q0.5": [
            2,
            2,
            2,
            2,
            2
        ],
        "q0.75": [
            2,
            5,
            7,
            11,
            15
        ],
        "q0.975": [
            2,
            35,
            66,
            68,
            72
        ]
    },
    "UVAFluX-Ensemble": {
        "target_end_date": [
            "2024-11-30",
            "2024-12-07",
            "2024-12-14",
            "2024-12-21",
            "2024-12-28"
        ],
        "q0.025": [
            0.0,
            0.0,
            0.0,
            0.0,
            0.0
        ],
        "q0.25": [
            1.0,
            1.0,
            0.0,
            0.0,
            1.0
        ],
        "q0.5": [
            2.0,
            3.0,
            2.0,
            2.0,
            3.0
        ],
        "q0.75": [
            3.0,
            4.0,
            3.0,
            4.0,
            4.0
        ],
        "q0.975": [
            5.0,
            6.0,
            6.0,
            7.0,
            8.0
        ]
    },
    "UGA_CEID-Walk": {
        "target_end_date": [
            "2024-12-07",
            "2024-12-14",
            "2024-12-21",
            "2024-12-28"
        ],
        "q0.025": [
            0.0,
            0.0,
            0.0,
            0.0
        ],
        "q0.25": [
            1.266,
            0.851,
            0.47,
            0.0
        ],
        "q0.5": [
            2.201,
            2.211,
            1.909,
            1.708
        ],
        "q0.75": [
            2.677,
            3.141,
            3.412,
            3.47
        ],
        "q0.975": [
            4.009,
            5.837,
            5.803,
            7.091
        ]
    },
    "NEU_ISI-FluBcast": {
        "target_end_date": [
            "2024-12-07",
            "2024-12-14",
            "2024-12-21",
            "2024-12-28"
        ],
        "q0.025": [
            0.0,
            0.0,
            0.0,
            0.0
        ],
        "q0.25": [
            0.0,
            0.0,
            0.0,
            0.0
        ],
        "q0.5": [
            1.0,
            1.0,
            1.0,
            1.0
        ],
        "q0.75": [
            2.0,
            2.0,
            2.0,
            2.0
        ],
        "q0.975": [
            6.0,
            7.0,
            8.0,
            11.0
        ]
    },
    "UM-DeepOutbreak": {
        "target_end_date": [
            "2024-12-07",
            "2024-12-14",
            "2024-12-21",
            "2024-12-28"
        ],
        "q0.025": [
            0.0,
            0.0,
            0.1111774444580078,
            3.906131782531739
        ],
        "q0.25": [
            0.0,
            3.324694124650958,
            10.842507557809354,
            12.705520259857174
        ],
        "q0.5": [
            0.6081302613019943,
            5.940219268798828,
            12.977496266365051,
            16.700256004333497
        ],
        "q0.75": [
            2.2841553392155465,
            8.519654782819746,
            14.433995051443576,
            20.379982364654545
        ],
        "q0.975": [
            6.078752815723419,
            18.25570011138916,
            25.16532516479492,
            29.17937084197998
        ]
    },
    "SigSci-TSENS": {
        "target_end_date": [
            "2024-12-07",
            "2024-12-14",
            "2024-12-21",
            "2024-12-28"
        ],
        "q0.025": [
            0.0,
            0.0,
            0.0,
            0.0
        ],
        "q0.25": [
            0.0,
            0.0,
            0.0,
            0.0
        ],
        "q0.5": [
            5.0,
            8.0,
            12.0,
            18.0
        ],
        "q0.75": [
            13.0,
            21.0,
            30.0,
            38.0
        ],
        "q0.975": [
            29.0,
            46.0,
            62.0,
            77.0
        ]
    },
    "fjordhest-ensemble": {
        "target_end_date": [
            "2024-11-30",
            "2024-12-07",
            "2024-12-14",
            "2024-12-21",
            "2024-12-28"
        ],
        "q0.025": [
            0.0,
            0.0,
            0.0,
            0.0,
            0.0
        ],
        "q0.25": [
            0.0,
            0.67,
            0.78,
            0.79,
            0.88
        ],
        "q0.5": [
            2.39,
            2.79,
            3.12,
            2.98,
            4.03
        ],
        "q0.75": [
            11.35,
            7.43,
            10.65,
            13.52,
            15.79
        ],
        "q0.975": [
            24.69,
            16.96,
            27.15,
            35.31,
            42.52
        ]
    },
    "Stevens-ILIForecast": {
        "target_end_date": [
            "2024-11-30",
            "2024-12-07",
            "2024-12-14",
            "2024-12-21",
            "2024-12-28"
        ],
        "q0.025": [
            0,
            0,
            0,
            0,
            0
        ],
        "q0.25": [
            0,
            0,
            0,
            0,
            0
        ],
        "q0.5": [
            7,
            6,
            4,
            0,
            2
        ],
        "q0.75": [
            8,
            10,
            8,
            8,
            4
        ],
        "q0.975": [
            16,
            14,
            15,
            17,
            20
        ]
    },
    "OHT_JHU-nbxd": {
        "target_end_date": [
            "2024-11-30",
            "2024-12-07",
            "2024-12-14",
            "2024-12-21",
            "2024-12-28"
        ],
        "q0.025": [
            0.18,
            0.4,
            0.79,
            1.68,
            2.65
        ],
        "q0.25": [
            0.72,
            1.65,
            3.25,
            6.49,
            9.9
        ],
        "q0.5": [
            1.36,
            3.13,
            6.16,
            11.96,
            18.01
        ],
        "q0.75": [
            2.41,
            5.57,
            10.98,
            20.84,
            31.05
        ],
        "q0.975": [
            6.27,
            14.61,
            28.73,
            52.75,
            77.38
        ]
    },
    "CEPH-Rtrend_fluH": {
        "target_end_date": [
            "2024-12-07",
            "2024-12-14",
            "2024-12-21",
            "2024-12-28"
        ],
        "q0.025": [
            1.0,
            0.0,
            0.0,
            0.0
        ],
        "q0.25": [
            2.0,
            2.0,
            2.0,
            2.0
        ],
        "q0.5": [
            3.0,
            4.0,
            5.0,
            7.0
        ],
        "q0.75": [
            4.0,
            7.0,
            12.0,
            21.0
        ],
        "q0.975": [
            6.0,
            17.0,
            49.0,
            144.0
        ]
    },
    "JHUAPL-DMD": {
        "target_end_date": [
            "2024-11-30",
            "2024-12-07",
            "2024-12-14",
            "2024-12-21",
            "2024-12-28"
        ],
        "q0.025": [
            0.0,
            0.0,
            0.0,
            0.0,
            0.0
        ],
        "q0.25": [
            0.0,
            0.0,
            0.0,
            0.0,
            0.0
        ],
        "q0.5": [
            1.515109989,
            0.557314498,
            1.152881856,
            0.695720264,
            1.591923664
        ],
        "q0.75": [
            12.30392869,
            16.81939587,
            18.09248843,
            20.97361378,
            25.39555757
        ],
        "q0.975": [
            34.7606914,
            56.33884527,
            68.77205682,
            102.7004949,
            163.7027906
        ]
    },
    "NIH-Flu_ARIMA": {
        "target_end_date": [
            "2024-12-07",
            "2024-12-14",
            "2024-12-21",
            "2024-12-28"
        ],
        "q0.025": [
            2.0,
            1.0,
            1.0,
            2.0
        ],
        "q0.25": [
            2.0,
            2.0,
            3.0,
            4.0
        ],
        "q0.5": [
            2.0,
            3.0,
            4.0,
            6.0
        ],
        "q0.75": [
            3.0,
            3.0,
            5.0,
            8.0
        ],
        "q0.975": [
            4.0,
            5.0,
            9.0,
            14.0
        ]
    }
}