{
    "JHU_CSSE-CSSE_Ensemble": {
        "target_end_date": [
            "2024-11-30",
            "2024-12-07",
            "2024-12-14",
            "2024-12-21"
        ],
        "q0.025": [
            29.0,
            42.48333333333333,
            63.96666666666666,
            66.0
        ],
        "q0.25": [
            89.66666666666667,
            113.0,
            132.0,
            144.0
        ],
        "q0.5": [
            122.33333333333331,
            153.5,
            176.0,
            195.33333333333331
        ],
        "q0.75": [
            156.33333333333334,
            190.5,
            223.33333333333331,
            253.33333333333331
        ],
        "q0.975": [
            219.01666666666665,
            275.8666666666666,
            320.7,
            364.7166666666666
        ]
    },
    "MIGHTE-Joint": {
        "target_end_date": [
            "2024-11-30",
            "2024-12-07",
            "2024-12-14",
            "2024-12-21"
        ],
        "q0.025": [
            42.0,
            39.0,
            34.0,
            35.0
        ],
        "q0.25": [
            54.0,
            60.0,
            60.0,
            70.0
        ],
        "q0.5": [
            61.0,
            74.0,
            79.0,
            98.0
        ],
        "q0.75": [
            68.0,
            90.0,
            102.0,
            134.0
        ],
        "q0.975": [
            85.0,
            129.0,
            162.0,
            231.0
        ]
    },
    "LUcompUncertLab-chimera": {
        "target_end_date": [
            "2024-11-23",
            "2024-11-30",
            "2024-12-07",
            "2024-12-14",
            "2024-12-21"
        ],
        "q0.025": [
            50,
            58,
            54,
            52,
            56
        ],
        "q0.25": [
            70,
            84,
            82,
            80,
            85
        ],
        "q0.5": [
            85,
            102,
            100,
            99,
            104
        ],
        "q0.75": [
            103,
            123,
            122,
            122,
            127
        ],
        "q0.975": [
            148,
            179,
            180,
            179,
            189
        ]
    },
    "UMass-flusion": {
        "target_end_date": [
            "2024-11-30",
            "2024-12-07",
            "2024-12-14",
            "2024-12-21"
        ],
        "q0.025": [
            23.0561352152931,
            16.4249282615695,
            13.6799324419138,
            12.6884222267925
        ],
        "q0.25": [
            41.3341443398945,
            40.8424193448554,
            41.1016581691575,
            39.8829983796864
        ],
        "q0.5": [
            54.9077619407983,
            61.2168738322,
            68.9555973246111,
            71.7613549222457
        ],
        "q0.75": [
            72.4313073599914,
            85.3473097948358,
            105.393346400641,
            115.739474656055
        ],
        "q0.975": [
            115.021945155344,
            151.707333367346,
            186.187080536129,
            224.602628883243
        ]
    },
    "UMass-trends_ensemble": {
        "target_end_date": [
            "2024-11-30",
            "2024-12-07",
            "2024-12-14",
            "2024-12-21"
        ],
        "q0.025": [
            12.5,
            2.0,
            0.0,
            0.0
        ],
        "q0.25": [
            30.5,
            29.5,
            26.5,
            25.0
        ],
        "q0.5": [
            51.5,
            50.5,
            52.0,
            54.0
        ],
        "q0.75": [
            68.0,
            78.0,
            84.0,
            92.0
        ],
        "q0.975": [
            84.5,
            115.0,
            139.0,
            161.5
        ]
    },
    "PSI-PROF": {
        "target_end_date": [
            "2024-11-30",
            "2024-12-07",
            "2024-12-14",
            "2024-12-21"
        ],
        "q0.025": [
            24.0,
            16.0,
            10.0,
            7.0
        ],
        "q0.25": [
            51.0,
            38.0,
            26.0,
            18.0
        ],
        "q0.5": [
            87.0,
            72.0,
            55.0,
            39.0
        ],
        "q0.75": [
            131.0,
            145.0,
            144.0,
            129.0
        ],
        "q0.975": [
            219.05,
            300.07,
            400.07,
            519.0
        ]
    },
    "NEU_ISI-AdaptiveEnsemble": {
        "target_end_date": [
            "2024-11-30",
            "2024-12-07",
            "2024-12-14",
            "2024-12-21"
        ],
        "q0.025": [
            33.0,
            44.0,
            58.0,
            62.0
        ],
        "q0.25": [
            51.0,
            63.0,
            84.0,
            102.0
        ],
        "q0.5": [
            64.0,
            79.0,
            106.0,
            123.0
        ],
        "q0.75": [
            80.0,
            104.0,
            130.0,
            178.0
        ],
        "q0.975": [
            102.0,
            133.0,
            192.0,
            274.0
        ]
    },
    "VTSanghani-PRIME": {
        "target_end_date": [
            "2024-11-23",
            "2024-11-30",
            "2024-12-07",
            "2024-12-14",
            "2024-12-21"
        ],
        "q0.025": [
            13.0,
            66.0,
            98.0,
            92.0,
            81.0
        ],
        "q0.25": [
            75.0,
            132.0,
            164.0,
            158.0,
            152.0
        ],
        "q0.5": [
            108.0,
            167.0,
            198.0,
            192.0,
            186.0
        ],
        "q0.75": [
            142.0,
            201.0,
            231.0,
            224.0,
            221.0
        ],
        "q0.975": [
            205.0,
            265.0,
            295.0,
            290.0,
            287.0
        ]
    },
    "UGA_flucast-INFLAenza": {
        "target_end_date": [
            "2024-11-30",
            "2024-12-07",
            "2024-12-14",
            "2024-12-21"
        ],
        "q0.025": [
            45,
            46,
            48,
            56
        ],
        "q0.25": [
            68,
            80,
            92,
            114
        ],
        "q0.5": [
            85,
            106,
            125,
            162
        ],
        "q0.75": [
            105,
            140,
            173,
            227
        ],
        "q0.975": [
            153,
            227,
            319,
            443
        ]
    },
    "MOBS-GLEAM_FLUH": {
        "target_end_date": [
            "2024-11-23",
            "2024-11-30",
            "2024-12-07",
            "2024-12-14",
            "2024-12-21"
        ],
        "q0.025": [
            35.829,
            28.898,
            26.294,
            25.079,
            25.078
        ],
        "q0.25": [
            45.581,
            47.777,
            49.373,
            51.125,
            52.85
        ],
        "q0.5": [
            51.841,
            60.104,
            63.501,
            69.175,
            75.235
        ],
        "q0.75": [
            56.652,
            72.913,
            80.1,
            91.265,
            103.119
        ],
        "q0.975": [
            60.679,
            99.294,
            114.298,
            145.005,
            183.758
        ]
    },
    "ISU_NiemiLab-GPE": {
        "target_end_date": [
            "2024-11-30"
        ],
        "q0.025": [
            24.9552764442481
        ],
        "q0.25": [
            36.8769971643953
        ],
        "q0.5": [
            47.4137015698603
        ],
        "q0.75": [
            55.9656570951195
        ],
        "q0.975": [
            69.3101414058325
        ]
    },
    "MIGHTE-Nsemble": {
        "target_end_date": [
            "2024-11-30",
            "2024-12-07",
            "2024-12-14",
            "2024-12-21"
        ],
        "q0.025": [
            40.0,
            37.0,
            35.0,
            7.0
        ],
        "q0.25": [
            52.0,
            60.0,
            63.0,
            63.0
        ],
        "q0.5": [
            60.0,
            77.0,
            84.0,
            107.0
        ],
        "q0.75": [
            68.0,
            96.0,
            110.0,
            159.0
        ],
        "q0.975": [
            87.0,
            144.0,
            177.0,
            278.0
        ]
    },
    "FluSight-lop_norm": {
        "target_end_date": [
            "2024-11-23",
            "2024-11-30",
            "2024-12-07",
            "2024-12-14",
            "2024-12-21"
        ],
        "q0.025": [
            0,
            12,
            5,
            2,
            0
        ],
        "q0.25": [
            43,
            44,
            45,
            45,
            42
        ],
        "q0.5": [
            66,
            63,
            71,
            80,
            87
        ],
        "q0.75": [
            88,
            88,
            109,
            127,
            152
        ],
        "q0.975": [
            176,
            217,
            313,
            435,
            562
        ]
    },
    "CU-ensemble": {
        "target_end_date": [
            "2024-11-30",
            "2024-12-07",
            "2024-12-14",
            "2024-12-21"
        ],
        "q0.025": [
            11.0,
            9.0,
            10.0,
            16.0
        ],
        "q0.25": [
            36.0,
            43.0,
            52.0,
            77.0
        ],
        "q0.5": [
            62.0,
            79.0,
            111.0,
            138.0
        ],
        "q0.75": [
            85.0,
            119.0,
            170.0,
            213.0
        ],
        "q0.975": [
            156.0,
            218.0,
            320.0,
            377.0
        ]
    },
    "CMU-TimeSeries": {
        "target_end_date": [
            "2024-11-23",
            "2024-11-30",
            "2024-12-07",
            "2024-12-14",
            "2024-12-21"
        ],
        "q0.025": [
            43.50741419183027,
            42.64424370369076,
            42.73999286312552,
            42.92374894950871,
            42.9690207320159
        ],
        "q0.25": [
            66.14347500952819,
            69.50540800884315,
            75.34746647185695,
            81.56935621742359,
            87.87237537192958
        ],
        "q0.5": [
            74.40116076004524,
            84.18702497713306,
            97.07631511122956,
            114.13342941300276,
            145.0397723446895
        ],
        "q0.75": [
            90.55499235524697,
            141.97547519233208,
            196.2052041771776,
            301.03479614926295,
            294.48122349719114
        ],
        "q0.975": [
            362.9698803552176,
            606.217647957374,
            660.1074890778917,
            684.0106673094216,
            699.6322094573982
        ]
    },
    "FluSight-ensemble": {
        "target_end_date": [
            "2024-11-23",
            "2024-11-30",
            "2024-12-07",
            "2024-12-14",
            "2024-12-21"
        ],
        "q0.025": [
            39.0,
            26.0,
            21.0,
            13.0,
            12.0
        ],
        "q0.25": [
            53.0,
            47.0,
            43.0,
            51.0,
            50.0
        ],
        "q0.5": [
            66.0,
            62.0,
            74.0,
            79.0,
            96.0
        ],
        "q0.75": [
            84.0,
            79.0,
            96.0,
            110.0,
            129.0
        ],
        "q0.975": [
            139.0,
            117.0,
            150.0,
            187.0,
            229.0
        ]
    },
    "UMass-AR2": {
        "target_end_date": [
            "2024-11-30",
            "2024-12-07",
            "2024-12-14",
            "2024-12-21"
        ],
        "q0.025": [
            9.55288962936312,
            0.0,
            0.0,
            0.0
        ],
        "q0.25": [
            24.773010720904427,
            19.04672472813317,
            17.505310305207317,
            16.047834723125888
        ],
        "q0.5": [
            35.8300149510045,
            35.973413477040275,
            36.56678373962256,
            39.85811605856928
        ],
        "q0.75": [
            47.50380971457632,
            55.92769347732859,
            63.2927893138103,
            72.23733081787003
        ],
        "q0.975": [
            78.5072552439024,
            110.38045688576064,
            137.1785319648755,
            171.59285446546912
        ]
    },
    "FluSight-baseline": {
        "target_end_date": [
            "2024-11-23",
            "2024-11-30",
            "2024-12-07",
            "2024-12-14",
            "2024-12-21"
        ],
        "q0.025": [
            47,
            0,
            0,
            0,
            0
        ],
        "q0.25": [
            47,
            33,
            22,
            11,
            1
        ],
        "q0.5": [
            47,
            47,
            47,
            47,
            47
        ],
        "q0.75": [
            47,
            61,
            74,
            86,
            98
        ],
        "q0.975": [
            47,
            193,
            257,
            274,
            294
        ]
    },
    "UVAFluX-Ensemble": {
        "target_end_date": [
            "2024-11-23",
            "2024-11-30",
            "2024-12-07",
            "2024-12-14",
            "2024-12-21"
        ],
        "q0.025": [
            48.0,
            24.0,
            15.0,
            7.0,
            4.0
        ],
        "q0.25": [
            62.0,
            47.0,
            58.0,
            65.0,
            42.0
        ],
        "q0.5": [
            70.0,
            62.0,
            75.0,
            84.0,
            65.0
        ],
        "q0.75": [
            77.0,
            78.0,
            93.0,
            103.0,
            93.0
        ],
        "q0.975": [
            94.0,
            116.0,
            134.0,
            149.0,
            167.0
        ]
    },
    "UM-DeepOutbreak": {
        "target_end_date": [
            "2024-11-30",
            "2024-12-07",
            "2024-12-14",
            "2024-12-21"
        ],
        "q0.025": [
            24.175500869750977,
            21.17225357055664,
            0.0,
            0.0
        ],
        "q0.25": [
            35.57072591781616,
            29.37342674823761,
            22.17612841342154,
            15.381184195041872
        ],
        "q0.5": [
            45.88953876495361,
            47.26895631790161,
            47.20410108566284,
            37.26882476806641
        ],
        "q0.75": [
            53.97469186782837,
            59.57624213603974,
            62.07188794400034,
            51.91248645925501
        ],
        "q0.975": [
            65.36991691589355,
            67.7774153137207,
            115.48041809082032,
            154.36173553466796
        ]
    },
    "SigSci-TSENS": {
        "target_end_date": [
            "2024-11-30",
            "2024-12-07",
            "2024-12-14",
            "2024-12-21"
        ],
        "q0.025": [
            0.0,
            0.0,
            0.0,
            0.0
        ],
        "q0.25": [
            34.0,
            32.0,
            37.0,
            50.0
        ],
        "q0.5": [
            56.0,
            65.0,
            78.0,
            96.0
        ],
        "q0.75": [
            79.0,
            99.0,
            118.0,
            141.0
        ],
        "q0.975": [
            121.0,
            162.0,
            195.0,
            228.0
        ]
    },
    "fjordhest-ensemble": {
        "target_end_date": [
            "2024-11-23",
            "2024-11-30",
            "2024-12-07",
            "2024-12-14",
            "2024-12-21"
        ],
        "q0.025": [
            0.0,
            0.0,
            0.09,
            0.0,
            0.0
        ],
        "q0.25": [
            38.46,
            36.83,
            34.0,
            32.74,
            35.2
        ],
        "q0.5": [
            61.7,
            56.41,
            55.22,
            54.88,
            58.53
        ],
        "q0.75": [
            83.22,
            75.02,
            82.62,
            86.76,
            94.24
        ],
        "q0.975": [
            129.1,
            120.95,
            149.87,
            194.06,
            228.19
        ]
    },
    "Stevens-ILIForecast": {
        "target_end_date": [
            "2024-11-23",
            "2024-11-30",
            "2024-12-07",
            "2024-12-14",
            "2024-12-21"
        ],
        "q0.025": [
            0,
            0,
            0,
            0,
            0
        ],
        "q0.25": [
            4,
            13,
            19,
            25,
            22
        ],
        "q0.5": [
            8,
            17,
            44,
            41,
            35
        ],
        "q0.75": [
            9,
            30,
            52,
            47,
            43
        ],
        "q0.975": [
            38,
            41,
            60,
            67,
            59
        ]
    },
    "OHT_JHU-nbxd": {
        "target_end_date": [
            "2024-11-23",
            "2024-11-30",
            "2024-12-07",
            "2024-12-14",
            "2024-12-21"
        ],
        "q0.025": [
            54.97,
            64.88,
            72.51,
            84.81,
            94.36
        ],
        "q0.25": [
            89.74,
            122.1,
            158.62,
            209.05,
            257.42
        ],
        "q0.5": [
            114.36,
            166.11,
            230.77,
            320.28,
            411.73
        ],
        "q0.75": [
            144.37,
            222.62,
            328.43,
            477.04,
            636.59
        ],
        "q0.975": [
            219.73,
            374.6,
            609.6,
            951.95,
            1346.57
        ]
    },
    "CEPH-Rtrend_fluH": {
        "target_end_date": [
            "2024-11-30",
            "2024-12-07",
            "2024-12-14",
            "2024-12-21"
        ],
        "q0.025": [
            52.0,
            37.0,
            27.0,
            18.0
        ],
        "q0.25": [
            71.0,
            71.0,
            70.0,
            67.0
        ],
        "q0.5": [
            84.0,
            102.0,
            118.0,
            134.0
        ],
        "q0.75": [
            100.0,
            143.0,
            196.0,
            254.0
        ],
        "q0.975": [
            135.0,
            258.0,
            453.0,
            700.0
        ]
    },
    "JHUAPL-DMD": {
        "target_end_date": [
            "2024-11-23",
            "2024-11-30",
            "2024-12-07",
            "2024-12-14",
            "2024-12-21"
        ],
        "q0.025": [
            0.0,
            0.0,
            0.0,
            0.0,
            0.0
        ],
        "q0.25": [
            9.597481999,
            27.97435469,
            20.69570929,
            23.16506718,
            11.42796566
        ],
        "q0.5": [
            46.7490582,
            86.18516375,
            96.23094538,
            112.6541508,
            121.747935
        ],
        "q0.75": [
            84.75136415,
            150.4355361,
            178.2976733,
            229.1257358,
            279.6121005
        ],
        "q0.975": [
            152.7823363,
            330.6154785,
            442.1862284,
            661.1757699,
            948.3081468
        ]
    },
    "NIH-Flu_ARIMA": {
        "target_end_date": [
            "2024-11-30",
            "2024-12-07",
            "2024-12-14",
            "2024-12-21"
        ],
        "q0.025": [
            30.0,
            22.0,
            19.0,
            20.0
        ],
        "q0.25": [
            38.0,
            34.0,
            36.0,
            42.0
        ],
        "q0.5": [
            41.0,
            42.0,
            48.0,
            59.0
        ],
        "q0.75": [
            46.0,
            51.0,
            63.0,
            83.0
        ],
        "q0.975": [
            58.0,
            76.0,
            111.0,
            156.0
        ]
    }
}